pypowerprojects/captcha.py
pypowerprojects/currency.py
pypowerprojects/gmail.py
pypowerprojects/instagram.py
pypowerprojects/tictactoe.py
pypowerprojects-1.1.6.dist-info/LICENSE.txt
pypowerprojects-1.1.6.dist-info/METADATA
pypowerprojects-1.1.6.dist-info/WHEEL
pypowerprojects-1.1.6.dist-info/entry_points.txt
pypowerprojects-1.1.6.dist-info/top_level.txt
pypowerprojects-1.1.6.dist-info/RECORD
